fidel/README.md
fidel/__init__.py
fidel/main.py
fidel/data/word_list.txt
fidel/helpers/filter.py
fidel/helpers/__pycache__/filter.cpython-310.pyc
fidel/utilities/dictionary.py
fidel/utilities/word.py
fidel/utilities/__pycache__/dictionary.cpython-310.pyc
fidel/utilities/__pycache__/word.cpython-310.pyc
fidel-0.0.10.dist-info/LICENSE
fidel-0.0.10.dist-info/METADATA
fidel-0.0.10.dist-info/WHEEL
fidel-0.0.10.dist-info/top_level.txt
fidel-0.0.10.dist-info/RECORD
