Metadata-Version: 2.1
Name: fidel
Version: 0.0.10
Summary: Python package that can change Amharic language that written in English alphabet to Amharic alphabet character.
Author: Niftalem Yeneneh
Author-email: ny.dev0.em@gmail.com
Keywords: python,amharic,english to amharic,ethiopia,translate,fidel
License-File: LICENSE
Requires-Dist: symspellpy (==6.7.1)
